leapserver/__init__.py
leapserver/server.py
leapserver-2020.3.27.dist-info/METADATA
leapserver-2020.3.27.dist-info/WHEEL
leapserver-2020.3.27.dist-info/top_level.txt
leapserver-2020.3.27.dist-info/RECORD
