Metadata-Version: 2.1
Name: leapserver
Version: 2020.3.27
Summary: a server for run python on web
Home-page: http://github.com/XRDX/pyleap
Author: Vic Wang
Author-email: 305880887@qq.com
License: UNKNOWN
Platform: UNKNOWN
Classifier: Programming Language :: Python :: 3
Classifier: License :: OSI Approved :: BSD License
Classifier: Operating System :: OS Independent
